hydroengine/__init__.py
hydroengine/cli.py
hydroengine-0.0.30.dist-info/METADATA
hydroengine-0.0.30.dist-info/RECORD
hydroengine-0.0.30.dist-info/WHEEL
hydroengine-0.0.30.dist-info/entry_points.txt
hydroengine-0.0.30.dist-info/top_level.txt
