Metadata-Version: 2.1
Name: hydroengine
Version: 0.0.30
Summary: Command-line interface for Hydro Engine
Home-page: https://github.com/gena/hydroengine
Author: Gennadii Donchyts
Author-email: gennadiy.donchyts@gmail.com
License: MIT license
Keywords: hydroengine
Platform: UNKNOWN
Classifier: Development Status :: 2 - Pre-Alpha
Classifier: Intended Audience :: Developers
Classifier: License :: OSI Approved :: MIT License
Classifier: Natural Language :: English
Classifier: Programming Language :: Python :: 2
Classifier: Programming Language :: Python :: 2.7
Classifier: Programming Language :: Python :: 3
Classifier: Programming Language :: Python :: 3.4
Classifier: Programming Language :: Python :: 3.5
Classifier: Programming Language :: Python :: 3.6
Classifier: Programming Language :: Python :: 3.7
Requires-Dist: Click (>=6.0)
Requires-Dist: requests (>=2.12)
